{"note":"This file is an internal implementation detail to speed up HTML report generation. Its format can change at any time. You might be looking for the JSON report: https://coverage.rtfd.io/cmd.html#cmd-json","format":5,"version":"7.6.0","globals":"08955dd7d5aaf7bf8ab9c6d037be733e","files":{"z_145eef247bfb46b6___init___py":{"hash":"e6baa73cda2916dad605215f937a92e1","index":{"url":"z_145eef247bfb46b6___init___py.html","file":"src\\__init__.py","description":"","nums":{"precision":0,"n_files":1,"n_statements":0,"n_excluded":0,"n_missing":0,"n_branches":0,"n_partial_branches":0,"n_missing_branches":0}}},"z_145eef247bfb46b6_main_py":{"hash":"f9aa4b76b84900329bce6096ac942b2e","index":{"url":"z_145eef247bfb46b6_main_py.html","file":"src\\main.py","description":"","nums":{"precision":0,"n_files":1,"n_statements":15,"n_excluded":0,"n_missing":12,"n_branches":0,"n_partial_branches":0,"n_missing_branches":0}}},"z_145eef247bfb46b6_category_py":{"hash":"8343f814a4eed7681a7dc7d79dc181f1","index":{"url":"z_145eef247bfb46b6_category_py.html","file":"src\\category.py","description":"","nums":{"precision":0,"n_files":1,"n_statements":36,"n_excluded":0,"n_missing":5,"n_branches":0,"n_partial_branches":0,"n_missing_branches":0}}},"z_145eef247bfb46b6_lawngrass_py":{"hash":"048e47f95a46e28f156fba77cd8c2ca1","index":{"url":"z_145eef247bfb46b6_lawngrass_py.html","file":"src\\lawngrass.py","description":"","nums":{"precision":0,"n_files":1,"n_statements":13,"n_excluded":0,"n_missing":2,"n_branches":0,"n_partial_branches":0,"n_missing_branches":0}}},"z_145eef247bfb46b6_product_py":{"hash":"3696a6e3bb8022d81539bd26a42dfbc8","index":{"url":"z_145eef247bfb46b6_product_py.html","file":"src\\product.py","description":"","nums":{"precision":0,"n_files":1,"n_statements":38,"n_excluded":0,"n_missing":5,"n_branches":0,"n_partial_branches":0,"n_missing_branches":0}}},"z_145eef247bfb46b6_smartphone_py":{"hash":"a6fb2d9b0a56cb1f1f86881140d8c1b0","index":{"url":"z_145eef247bfb46b6_smartphone_py.html","file":"src\\smartphone.py","description":"","nums":{"precision":0,"n_files":1,"n_statements":14,"n_excluded":0,"n_missing":1,"n_branches":0,"n_partial_branches":0,"n_missing_branches":0}}},"z_145eef247bfb46b6_base_product_py":{"hash":"858e396a5ab87c1694dc453893f026b3","index":{"url":"z_145eef247bfb46b6_base_product_py.html","file":"src\\base_product.py","description":"","nums":{"precision":0,"n_files":1,"n_statements":6,"n_excluded":0,"n_missing":1,"n_branches":0,"n_partial_branches":0,"n_missing_branches":0}}},"z_145eef247bfb46b6_print_mixin_py":{"hash":"2a8a42dd90c48d91641f81d59f7cbfd4","index":{"url":"z_145eef247bfb46b6_print_mixin_py.html","file":"src\\print_mixin.py","description":"","nums":{"precision":0,"n_files":1,"n_statements":6,"n_excluded":0,"n_missing":0,"n_branches":0,"n_partial_branches":0,"n_missing_branches":0}}}}}